{"ONTa1ZKFbckyW5o5ADzlUw==":"mbr-1920x1080.jpg","/qEuSKR856TWrQJkNL+WJQ==":"mbr-1920x1280.jpg","w8/HtPMkbqoLg6QBcJNuqg==":"picsart_05-06-10.52.14(1)-176x81.jpg","ptpjSe+Wir9300iZMtiZXA==":"picsart_05-06-10.52.14(1)-1-176x81.jpg","klERilHjWBGsjbUIYrsuzg==":"mbr-1920x1277.jpg","jXsBZX46UuB3yTC50/00ag==":"mbr-1-1920x1080.jpg","BG/5l7NzMpXe1cuxHeHzUw==":"mbr-1920x1357.jpg","kE8lhDVoSCqmFiqlJNREIQ==":"webp.net-resizeimage-676x434.jpg","4RnHHtuqBorj+WjYtDNobg==":"t%20%20a%20%20c-676x507.jpg","xphFmF4+zlzUj5gFhFD1nA==":"t%20%20a%20%20c-676x507.jpg","huopeqa+rXoDn2ySkfsOfg==":"t%20%20a%20%20c-676x507.jpg","OTf1Xt4/YffyOMo5DmSiTA==":"img_0068%20(copy)-676x451.jpg","dg5HCqcFfm28btdB9Hzhrw==":"12345-940x464.jpg","qo0970KcjWY31y1L/xI9Vg==":"contemporary-villa%20finel-1563x955.jpg","Nz3o0l9weQrdPM3Y2QYgGA==":"drop-dead-gorgeous-modern-house-designs%20finel-1153x677.jpg","IGo/DSmMXJxLWW186rmtOA==":"dk-129x132.png","jxpTyOPDvn0taHRcPAiHww==":"mbr-1920x1081.jpg","3JcIrGtLzgauk8D6cG17cA==":"mbr-1-1920x1280.jpg","picbZKn0xcTPNJjB0Wtfrw==":"mbr-2-1920x1280.jpg","IL4h1srOCODo4yCDPdCFZw==":"sandip%20ji-1200x850.jpg","5XIBcz0jbNYo/EVTcDsgpQ==":"sandip%20ji-1200x850.jpg","Mzmh07KM1UMnbY/4v6qwHA==":"modern-house-design-pictures-house-designs-modern-home-design-pictures-1000x667.jpg","swg8ktqt/z6rxmIL+gCkaA==":"a98bbbb68766ccbdb5a9db9c18b65efd_large-800x532.jpg","64kfHitEv4pN2vlkInx45g==":"img-4996-1200x800.jpg","Q254zl/1P2D56fRvxqRvxQ==":"img-4997-1200x800.jpg","l8ZlIQWASavFRBU0dvi7EA==":"img-4996-1098x732.jpg","YauvyjkS9NtUYPFy5ybFPw==":"img-4997-1098x732.jpg","Liy72r123+PJeWCqyGad2g==":"yoga-retreat-himalyas-uttrakhand-ukhimath-4-1170x585.jpg","vNl40stMmFOsqxTgKt8IRA==":"eco-friendly-house-1200x800.jpg","Ip3kP1rScDxUN6FOZMaPEw==":"eco-friendly-house-1-1200x800.jpg","ZpyHLEGBPeaNjQTw0c2QPw==":"12744694_1568026450154385_279822552007405968_n-540x720.jpg","CP+RZ0F8y4M1u0jlqqxVpQ==":"19366308_1758287951128233_6444035210857236367_n-533x800.jpg","knubPgtiFo9D5RbkaeqliA==":"20914570_1538488169548314_7982883907528228685_n-960x720.jpg","dmE+5sbmVpi00NSerZm/FA==":"28958332_1862631274027233_2746489761676918784_n-640x480.jpg","7HraF/CA3cJ3BAMu00xtAA==":"33524345_1894732834150410_2660390957475692544_n-480x233.jpg","YeV98L3aKKyOA+gUi80yMw==":"35463304_1904578673165826_6359431055824388096_n-631x621.jpg","WFoNHUxJfIB2T8gBi6LgMA==":"20800358_1784188641871497_8214290222610443655_n-705x924.jpg","h2QnUmN2A+m6PlAib/0fCg==":"19243068_1471880766209055_6189842212296965785_o-1092x310.jpg","QEUDvykOn3s2D5HtgUN/yw==":"jumbotron.jpg","kHiMZaK2EfO1jvQ2DLoKeQ==":"22582069_276034119554867_7540405366958325760_n-376x470.jpg","mUYC/XnEQMdMtfNT8u/gJw==":"bhakarbadi.gif","YS46Sa02uk3zpnRG5Mn1Bw==":"bhakarbadi-1.gif","EIMbsFPXGBQxcYS0ltjk5g==":"jhangora%20para.gif","Ko1mFARfEdgdsRTVJSWGZQ==":"bhakarbadi-2.gif","Ksnnvq24WxctAU6qzvsyow==":"jhangora%20para.gif","ZWtY9V5lWfs6EJsybINYDg==":"untitled-1.gif","q6GagNR1v9F5V/adRmMyuw==":"untitled-2.gif","3J/2BpQI4xVsdtprjhCu/Q==":"singori%20finel-376x212.jpg","MEL4vJfQvbAd8G6/COjPVQ==":"singori%20finel-376x212.jpg","u4pcgMuj3bvGr5rtWco37Q==":"singori%20finel-376x212.jpg","ltLK7HXD1u+mN4vm+0w2NQ==":"22582069_276034119554867_7540405366958325760_n-750x937.jpg","6Dh/HMJvisB4PPcooXUZDw==":"bakabadi%20finel11-1280x720.jpg","0OOE1Usrtktm437Z/qTMRQ==":"background2.jpg","euUIOcYkff92RUKmDa0/Wg==":"jhangora%20para%20finel-1280x720.jpg","QV7VT4BLXVqgzxk8iJAHxA==":"jhangora%20para%20finel-1280x720.jpg","sZDaeqUa0K/A2jp4sO3Teg==":"matri%20finel-1920x1080.jpg","nJY2AENbm3FN7UQ+Ypi0fg==":"jhangora%20para%20finel-1280x720.jpg","+eW+7V5ZiyXU9wHfywxxuA==":"singori%20finel-1280x720.jpg","WuUaXb9l3QHEi7g8D8te1g==":"dk-122x125.png","eHNhG4LhwWheNGcxE9zbQw==":"22582069_276034119554867_7540405366958325760_n-1-750x937.jpg","0GgiIBLE92ZrF+60IXHIsg==":"bakabadi%20finel11-1046x588.jpg","ou/YhDaDfJ8ougQ+AgsqjQ==":"bakabadi%20finel11-1280x720.jpg","8gfIjYwBX5RZSNF2avm+XA==":"bakabadi%20finel11-1280x720.jpg","bCLgVHWXpXBagtwhOlL6kg==":"bakabadi%20finel11-1014x570.jpg","kKmqy8+UBz+xSWATNV5HbA==":"bakabadi%20finel11-952x536.jpg","ON0rGwCd4Q0KxMHSecPSpw==":"ragi-660x495.jpg","lAY3ATQpgiELgiFDYqCSew==":"barnyard_millet_dsc5318_1400x-832x832.jpg","w3I5zHwu9optm2FDz5NBhw==":"bhakarbadi-3.gif","ltw0MLvKRUHrFOycHpCKUA==":"jhangora%20para.gif","B4zQiqRrwhmgKkLqbBhjOw==":"jhangora%20para.gif","TiHeQNl0r9nYPlfGXBUkMw==":"untitled-3.gif","zIZIvZuwrdcM2I9P18TRfg==":"millet-800x500.jpg","ftESWxdOax+S194QUfP89g==":"ddasd-960x720.jpg","Rh74ej4zLVwjlG2KKUR+Yw==":"ddasd-1-960x720.jpg"}